bench/nist_msp_ftp_test.py
docs/conf.py
docs/examples/draw_entry.py
docs/examples/first_n_entries.py
docs/examples/readme.py
docs/examples/validate_library.py
mzspeclib/__init__.py
mzspeclib/analyte.py
mzspeclib/annotation.py
mzspeclib/attributes.py
mzspeclib/cluster.py
mzspeclib/const.py
mzspeclib/defaults.py
mzspeclib/draw.py
mzspeclib/ontology.py
mzspeclib/peak_list.py
mzspeclib/spectrum.py
mzspeclib/spectrum_library.py
mzspeclib/spectrum_library_collection.py
mzspeclib/spectrum_library_index.py
mzspeclib/universal_spectrum_identifier.py
mzspeclib/utils.py
mzspeclib/backends/__init__.py
mzspeclib/backends/base.py
mzspeclib/backends/bibliospec.py
mzspeclib/backends/diann.py
mzspeclib/backends/encyclopedia.py
mzspeclib/backends/json.py
mzspeclib/backends/memory.py
mzspeclib/backends/msp.py
mzspeclib/backends/spectronaut.py
mzspeclib/backends/sptxt.py
mzspeclib/backends/text.py
mzspeclib/backends/utils.py
mzspeclib/index/__init__.py
mzspeclib/index/base.py
mzspeclib/index/memory.py
mzspeclib/index/sql.py
mzspeclib/tools/__init__.py
mzspeclib/tools/cli.py
mzspeclib/tools/utils.py
mzspeclib/validate/__init__.py
mzspeclib/validate/level.py
mzspeclib/validate/object_rule.py
mzspeclib/validate/semantic_rule.py
mzspeclib/validate/validator.py
mzspeclib/validate/rules/__init__.py
mzspeclib/validate/rules/all.json
mzspeclib/validate/rules/base.json
mzspeclib/validate/rules/consensus.json
mzspeclib/validate/rules/convert_to_xlsx.py
mzspeclib/validate/rules/gold.json
mzspeclib/validate/rules/peptide.json
mzspeclib/validate/rules/silver.json
mzspeclib/validate/rules/single.json
mzspeclib/validate/rules/validator-rules-schema.json
mzspeclib/validate/rules/tmp/excel_terms_to_json_rules.py
mzspeclib-1.0.7.dist-info/licenses/LICENSE
tests/__init__.py
tests/common.py
tests/test_cluster.py
tests/test_index.py
tests/test_library.py
tests/test_library_backend.py
tests/test_msp_attributes.py
tests/test_spectrum.py
tests/test_validate.py
tests/test_data/generate_annotations.py
viewer/__init__.py
viewer/tables.py
mzspeclib-1.0.7.dist-info/METADATA
mzspeclib-1.0.7.dist-info/WHEEL
mzspeclib-1.0.7.dist-info/entry_points.txt
mzspeclib-1.0.7.dist-info/top_level.txt
mzspeclib-1.0.7.dist-info/RECORD
