Metadata-Version: 2.4
Name: mzspeclib
Version: 1.0.7
Summary: HUPO-PSI Spectral library format
Author-email: Joshua Klein <mobiusklein@gmail.com>, Ralf Gabriels <ralf@gabriels.dev>, Eric W Deutsch <edeutsch@systemsbiology.org>
License:                                  Apache License
Project-URL: Homepage, https://hupo-psi.github.io/mzSpecLib/
Project-URL: Repository, https://github.com/HUPO-PSI/mzspeclib-py.git
Project-URL: Documentation, https://mzspeclib-py.readthedocs.io/en/latest/
Project-URL: Issues, https://github.com/HUPO-PSI/mzspeclib-py/issues
Keywords: mass spectrometry,spectral library
Classifier: Intended Audience :: Science/Research
Classifier: Programming Language :: Python :: 3 :: Only
Classifier: Topic :: Scientific/Engineering :: Bio-Informatics
Classifier: Development Status :: 3 - Alpha
Classifier: License :: OSI Approved :: Apache Software License
Requires-Python: >=3.8
License-File: LICENSE
Requires-Dist: sqlalchemy
Requires-Dist: click
Requires-Dist: psims>=1.3.4
Requires-Dist: pyteomics>=4.5.3
Requires-Dist: mzpaf
Provides-Extra: test
Requires-Dist: jsonschema; extra == "test"
Provides-Extra: docs
Requires-Dist: sphinx; extra == "docs"
Requires-Dist: sphinx-rtd-theme; extra == "docs"
Requires-Dist: numpydoc<2,>=1; extra == "docs"
Requires-Dist: sphinx_click; extra == "docs"
Requires-Dist: myst-parser; extra == "docs"
Requires-Dist: sphinx-autobuild; extra == "docs"
Dynamic: license-file
